mpl_finance.py
mpl_finance-0.10.1.dist-info/LICENSE
mpl_finance-0.10.1.dist-info/METADATA
mpl_finance-0.10.1.dist-info/WHEEL
mpl_finance-0.10.1.dist-info/top_level.txt
mpl_finance-0.10.1.dist-info/RECORD
