Metadata-Version: 2.1
Name: mpl_finance
Version: 0.10.1
Summary: Finance plots using matplotlib
Home-page: http://github.com/matplotlib/mpl-finance
Author: MPL Developers
Author-email: matplotlib-users@python.org
License: BSD-style
Keywords: finance
Platform: Cross platform (Linux
Platform: Mac OSX
Platform: Windows)
Classifier: Development Status :: 7 - Inactive
Classifier: Programming Language :: Python :: 2
Classifier: Programming Language :: Python :: 2.7
Classifier: Programming Language :: Python :: 3
Classifier: Programming Language :: Python :: 3.3
Classifier: Programming Language :: Python :: 3.4
Classifier: Programming Language :: Python :: 3.5
Classifier: Programming Language :: Python :: 3.6
